pipa-0.1.0.dist-info/METADATA
pipa-0.1.0.dist-info/DESCRIPTION.rst
pipa-0.1.0.dist-info/entry_points.txt
pipa-0.1.0.dist-info/WHEEL
pipa-0.1.0.dist-info/RECORD
pipa-0.1.0.dist-info/pydist.json
pipa-0.1.0.dist-info/top_level.txt
pipa-0.1.0.data/scripts/pipa
pipa/util.py
pipa/__main__.py
pipa/server.py
pipa/__init__.py
pipa/certs.py
pipa/templates/project.html
pipa/templates/simple.html
