Metadata-Version: 2.0
Name: pipa
Version: 0.1.0
Summary: Simple HTTPS PyPI server
Home-page: https://pypi.python.org/pypi/pipa
Author: Matthew Iversen
Author-email: matt@notevencode.com
License: MIT
Platform: UNKNOWN
Classifier: Development Status :: 3 - Alpha
Classifier: Programming Language :: Python :: 3
Classifier: Programming Language :: Python :: 3.2
Classifier: Programming Language :: Python :: 3.3
Classifier: Programming Language :: Python :: 3.4
Classifier: License :: OSI Approved :: MIT License
Classifier: Topic :: Utilities
Classifier: Topic :: System :: Software Distribution
Classifier: Topic :: System :: Archiving :: Mirroring
Requires-Dist: cherrypy
Requires-Dist: pyOpenSSL
Requires-Dist: Jinja2
